ai/__init__.py
ai/solve.py
8puzz-0.0.1.dist-info/METADATA
8puzz-0.0.1.dist-info/WHEEL
8puzz-0.0.1.dist-info/top_level.txt
8puzz-0.0.1.dist-info/RECORD
