Metadata-Version: 2.1
Name: 8puzz
Version: 0.0.1
Summary: 8_puzzle_problem
Author: yuvraj
Author-email: yuvrajdevnani03@gmail.com
Keywords: python
Classifier: Development Status :: 1 - Planning
Classifier: Intended Audience :: Developers
Classifier: Programming Language :: Python :: 3
Classifier: Operating System :: Unix
Classifier: Operating System :: MacOS :: MacOS X
Classifier: Operating System :: Microsoft :: Windows
